sdks/__init__.py
sdks/models/__init__.py
sdks/models/common.py
sdks/models/test_events.py
sdks/terminals/__init__.py
sdks/terminals/crypto/__init__.py
sdks/terminals/crypto/crypto_terminal.py
sdks/terminals/crypto/menu.py
sdks/webull_sdk/__init__.py
sdks/webull_sdk/calendar.py
sdks/webull_sdk/capitalflow.py
sdks/webull_sdk/cost_distribution.py
sdks/webull_sdk/derivative_query.py
sdks/webull_sdk/etf_finder.py
sdks/webull_sdk/etf_holdings.py
sdks/webull_sdk/events.py
sdks/webull_sdk/financial_statement.py
sdks/webull_sdk/forecast.py
sdks/webull_sdk/institutional_holdings.py
sdks/webull_sdk/manage.py
sdks/webull_sdk/news.py
sdks/webull_sdk/shortinterest.py
sdks/webull_sdk/top_gainers.py
sdks/webull_sdk/top_options.py
sdks/webull_sdk/webull_data.py
sdks/webull_sdk/webull_sdk.py
polygon_finance-1.0.0.dist-info/METADATA
polygon_finance-1.0.0.dist-info/WHEEL
polygon_finance-1.0.0.dist-info/top_level.txt
polygon_finance-1.0.0.dist-info/RECORD
