Metadata-Version: 2.1
Name: polygon-finance
Version: 1.0.0
Summary: The real-time market analysis library that utilizes the real-time rest apis and websockets from polygon.io
Author: Charlies Vids
Author-email: chuckdustin12@gmail.com
Requires-Dist: aiofiles (==23.1.0)
Requires-Dist: aiohttp (==3.8.4)
Requires-Dist: aiosignal (==1.3.1)
Requires-Dist: anyio (==3.6.2)
Requires-Dist: async-timeout (==4.0.2)
Requires-Dist: attrs (==23.1.0)
Requires-Dist: beautifulsoup4 (==4.12.2)
Requires-Dist: bs4 (==0.0.1)
Requires-Dist: cachetools (==5.3.0)
Requires-Dist: certifi (==2022.12.7)
Requires-Dist: cffi (==1.15.1)
Requires-Dist: charset-normalizer (==3.1.0)
Requires-Dist: colorama (==0.4.6)
Requires-Dist: contourpy (==1.0.7)
Requires-Dist: cryptography (==40.0.2)
Requires-Dist: cycler (==0.11.0)
Requires-Dist: discord-webhook (==1.1.0)
Requires-Dist: disnake (==2.8.1)
Requires-Dist: filelock (==3.12.0)
Requires-Dist: fonttools (==4.39.4)
Requires-Dist: frozenlist (==1.3.3)
Requires-Dist: fsspec (==2023.5.0)
Requires-Dist: h11 (==0.14.0)
Requires-Dist: httpcore (==0.17.0)
Requires-Dist: httpx (==0.24.0)
Requires-Dist: huggingface-hub (==0.14.1)
Requires-Dist: idna (==3.4)
Requires-Dist: Jinja2 (==3.1.2)
Requires-Dist: kiwisolver (==1.4.4)
Requires-Dist: MarkupSafe (==2.1.2)
Requires-Dist: matplotlib (==3.7.1)
Requires-Dist: mplfinance (==0.12.9b7)
Requires-Dist: mpmath (==1.3.0)
Requires-Dist: multidict (==6.0.4)
Requires-Dist: mypy-extensions (==1.0.0)
Requires-Dist: networkx (==3.1)
Requires-Dist: numpy (==1.24.3)
Requires-Dist: openai (==0.27.6)
Requires-Dist: packaging (==23.1)
Requires-Dist: pandas (==2.0.1)
Requires-Dist: pdfminer.six (==20221105)
Requires-Dist: pdfplumber (==0.9.0)
Requires-Dist: Pillow (==9.5.0)
Requires-Dist: polygon (==1.1.0)
Requires-Dist: polygon-api-client (==1.8.5)
Requires-Dist: pycparser (==2.21)
Requires-Dist: pyimgur (==0.6.0)
Requires-Dist: pyparsing (==3.0.9)
Requires-Dist: PyPDF2 (==3.0.1)
Requires-Dist: pyre-extensions (==0.0.23)
Requires-Dist: python-dateutil (==2.8.2)
Requires-Dist: pytz (==2023.3)
Requires-Dist: PyYAML (==6.0)
Requires-Dist: regex (==2023.5.5)
Requires-Dist: requests (==2.30.0)
Requires-Dist: scipy (==1.10.1)
Requires-Dist: seaborn (==0.12.2)
Requires-Dist: six (==1.16.0)
Requires-Dist: sniffio (==1.3.0)
Requires-Dist: soupsieve (==2.4.1)
Requires-Dist: sympy (==1.12)
Requires-Dist: tabulate (==0.9.0)
Requires-Dist: tokenizers (==0.13.3)
Requires-Dist: torch (==2.0.1)
Requires-Dist: tqdm (==4.65.0)
Requires-Dist: transformers (==4.29.1)
Requires-Dist: typing-inspect (==0.8.0)
Requires-Dist: typing-extensions (==4.5.0)
Requires-Dist: tzdata (==2023.3)
Requires-Dist: urllib3 (==1.26.15)
Requires-Dist: Wand (==0.6.11)
Requires-Dist: websocket-client (==1.5.1)
Requires-Dist: websockets (==10.4)
Requires-Dist: yarl (==1.9.2)
